wheresmycar/__init__.py
wheresmycar/plate_detector.py
wheresmycar-0.0.2.5.dist-info/LICENSE.md
wheresmycar-0.0.2.5.dist-info/METADATA
wheresmycar-0.0.2.5.dist-info/WHEEL
wheresmycar-0.0.2.5.dist-info/top_level.txt
wheresmycar-0.0.2.5.dist-info/RECORD
