Metadata-Version: 2.1
Name: wheresmycar
Version: 0.0.2.5
Summary: Detect vehicle license plates
Author-email: Michał Dołbniak <michal.dolbniak@gmail.com>
Project-URL: Homepage, https://github.com/michdol/wheresmycar
Keywords: machine learning,object detection,educational
Classifier: License :: OSI Approved :: MIT License
Classifier: Programming Language :: Python
Classifier: Programming Language :: Python :: 3
Requires-Python: >=3.9
License-File: LICENSE.md
Requires-Dist: torch >=2.3.1
Requires-Dist: torchvision >=0.18.1
Requires-Dist: ultralytics >=8.2.42
Provides-Extra: dev
Requires-Dist: pylint ; extra == 'dev'
Requires-Dist: mypy ; extra == 'dev'
